qonstellation/__init__.py
qonstellation/__main__.py
qonstellation/config.cfg
qonstellation/feed.py
qonstellation/viewer.py
qonstellation-0.2.0.dist-info/LICENSE
qonstellation-0.2.0.dist-info/METADATA
qonstellation-0.2.0.dist-info/WHEEL
qonstellation-0.2.0.dist-info/entry_points.txt
qonstellation-0.2.0.dist-info/top_level.txt
qonstellation-0.2.0.dist-info/RECORD
