Metadata-Version: 2.1
Name: qonstellation
Version: 0.2.0
Summary: Qonstellation Client
Home-page: https://github.com/qonstellation/client
Author: Qonstellation LLC
Author-email: support@qonstellation.co
License: MIT
Platform: UNKNOWN
Classifier: License :: OSI Approved :: MIT License
Classifier: Programming Language :: Python
Classifier: Programming Language :: Python :: 2
Classifier: Programming Language :: Python :: 3
Requires-Dist: feedparser
Requires-Dist: html2text
Requires-Dist: importlib-resources
Requires-Dist: typing
